quantum_executor/__init__.py
quantum_executor/dispatch.py
quantum_executor/executor.py
quantum_executor/job_runner.py
quantum_executor/local_aer/__init__.py
quantum_executor/local_aer/device.py
quantum_executor/local_aer/provider.py
quantum_executor/policies/multiplier.py
quantum_executor/policies/simple_aggregate.py
quantum_executor/policies/uniform.py
quantum_executor/result_collector.py
quantum_executor/virtual_provider.py
quantum_executor-0.1.0.dist-info/LICENSE
quantum_executor-0.1.0.dist-info/METADATA
quantum_executor-0.1.0.dist-info/WHEEL
quantum_executor-0.1.0.dist-info/RECORD
