Metadata-Version: 2.3
Name: quantum-executor
Version: 0.1.0
Summary: Quantum Executor: A Unified Interface for Quantum Computing
License: AGPL-3.0-or-later
Keywords: quantum,quantum-computing,quantum-cloud,quantum-software-engineering,quantum-interface
Author: Giuseppe Bisicchia
Author-email: giuseppe.bisicchia@phd.unipi.it
Requires-Python: >=3.12,<4.0
Classifier: License :: OSI Approved :: GNU Affero General Public License v3 or later (AGPLv3+)
Classifier: Programming Language :: Python :: 3
Classifier: Programming Language :: Python :: 3.12
Classifier: Programming Language :: Python :: 3.13
Classifier: Topic :: Scientific/Engineering :: Information Analysis
Classifier: Topic :: Scientific/Engineering :: Physics
Requires-Dist: amazon-braket-sdk (>=1.91.2,<2.0.0)
Requires-Dist: cirq (>=1.5.0,<2.0.0)
Requires-Dist: qbraid[azure] (>=0.9.5,<0.10.0)
Requires-Dist: qiskit (>=2.0.0,<3.0.0)
Requires-Dist: qiskit-aer (>=0.17.0,<0.18.0)
Requires-Dist: qiskit-ibm-runtime (>=0.38.0,<0.39.0)
Project-URL: documentation, https://quantum-executor.readthedocs.io
Project-URL: homepage, https://github.com/GBisi/quantum-executor
Project-URL: repository, https://github.com/GBisi/quantum-executor
